letterenv/__init__.py
letterenv/letterenv.py
letterenv-0.1.5.dist-info/METADATA
letterenv-0.1.5.dist-info/WHEEL
letterenv-0.1.5.dist-info/RECORD
